email_actions/__init__.py
email_actions/config.py
email_actions/constants.py
email_actions/filters.py
email_actions/server.py
email_actions/plugins/__init__.py
email_actions/plugins/email.py
email_actions/plugins/exec.py
email_actions/plugins/join.py
email_actions-0.1.0.dist-info/DESCRIPTION.rst
email_actions-0.1.0.dist-info/METADATA
email_actions-0.1.0.dist-info/RECORD
email_actions-0.1.0.dist-info/WHEEL
email_actions-0.1.0.dist-info/entry_points.txt
email_actions-0.1.0.dist-info/metadata.json
email_actions-0.1.0.dist-info/top_level.txt
