Metadata-Version: 2.0
Name: email-actions
Version: 0.1.0
Summary: An SMTP server with a rules based engine to trigger   any actions (notifications/commands etc) based on the emails sent to   this server
Home-page: https://github.com/shantanugoel/email-actions/
Author: Shantanu Goel
Author-email: shantanu@shantanugoel.com
License: MIT
Keywords: email smtp notification trigger
Platform: UNKNOWN
Classifier: Development Status :: 4 - Beta
Classifier: License :: OSI Approved :: MIT License
Classifier: Operating System :: POSIX
Classifier: Natural Language :: English
Classifier: Operating System :: OS Independent
Classifier: Programming Language :: Python
Classifier: Programming Language :: Python :: 3
Classifier: Programming Language :: Python :: 3.4
Classifier: Programming Language :: Python :: 3.5
Classifier: Programming Language :: Python :: 3.6
Classifier: Topic :: Communications
Classifier: Topic :: Communications :: Email
Classifier: Topic :: Internet
Classifier: Topic :: Software Development :: Libraries
Classifier: Topic :: Software Development :: Libraries :: Python Modules
Classifier: Topic :: Utilities
Requires-Dist: aiosmtpd
Requires-Dist: requests
Requires-Dist: PyYAML
